pytinyopengl3.cpython-311-x86_64-linux-gnu.so
pytinydiffsim.cpython-311-x86_64-linux-gnu.so
tds_environments/cartpole_tds_env.py
tds_environments/reacher_tds_env.py
tds_environments/__init__.py
pytinydiffsim-0.9.5.dist-info/WHEEL
pytinydiffsim-0.9.5.dist-info/METADATA
pytinydiffsim-0.9.5.dist-info/top_level.txt
pytinydiffsim-0.9.5.dist-info/RECORD
pytinydiffsim-0.9.5.dist-info/LICENSE
